services/__init__.py
services/cli.py
services/services.py
services-0.1.1.dist-info/AUTHORS.rst
services-0.1.1.dist-info/LICENSE
services-0.1.1.dist-info/METADATA
services-0.1.1.dist-info/WHEEL
services-0.1.1.dist-info/entry_points.txt
services-0.1.1.dist-info/top_level.txt
services-0.1.1.dist-info/RECORD
