Metadata-Version: 1.1
Name: services
Version: 0.1.1
Summary: A Python package for helpful tooling.
Home-page: https://github.com/dshurick/services
Author: Devon Bradley Shurick
Author-email: dshurick@gmail.com
License: MIT license
Keywords: services
Platform: UNKNOWN
Classifier: Development Status :: 2 - Pre-Alpha
Classifier: Intended Audience :: Developers
Classifier: License :: OSI Approved :: MIT License
Classifier: Natural Language :: English
Classifier: Programming Language :: Python :: 2
Classifier: Programming Language :: Python :: 2.7
Classifier: Programming Language :: Python :: 3
Classifier: Programming Language :: Python :: 3.4
Classifier: Programming Language :: Python :: 3.5
Classifier: Programming Language :: Python :: 3.6
Classifier: Programming Language :: Python :: 3.7
